{
  "accountAssociation": {
    "header": "eyJmaWQiOjIxODIzMjUsInR5cGUiOiJjdXN0b2R5Iiwia2V5IjoiMHg2NTRkZkMxNEY0QjczN2M4NjM5OWY1MTcyMGJjNTlCNTdCM2VEQjc5In0",
    "payload": "eyJkb21haW4iOiJlcmM0NjI2LmZ1biJ9",
    "signature": "lhS8ZW/t66E5BaOI+nq0tsoZp9Vf2cD1HUcb8SEI5w47VSSBG6P+yq33wTXDGD1j6HNgRYv8OR7xc9ZGdCvemRs="
  },
  "miniapp": {
    "version": "1",
    "name": "Creator Vaults",
    "subtitle": "Creator coin vaults on Base",
    "description": "Deposit creator coins into vaults, track markets, and manage creator vault launches on Base.",
    "screenshotUrls": [
      "https://4626.fun/screenshot-portrait.png"
    ],
    "iconUrl": "https://4626.fun/miniapp-icon.png",
    "splashImageUrl": "https://4626.fun/miniapp-splash.png",
    "splashBackgroundColor": "#000000",
    "homeUrl": "https://4626.fun",
    "webhookUrl": "https://4626.fun/api/webhook",
    "canonicalDomain": "erc4626.fun",
    "requiredChains": [
      "eip155:8453"
    ],
    "requiredCapabilities": [
      "actions.ready",
      "actions.signIn",
      "wallet.getEthereumProvider"
    ],
    "primaryCategory": "finance",
    "tags": [
      "creator-coins",
      "vaults",
      "base",
      "zora"
    ],
    "heroImageUrl": "https://4626.fun/miniapp-hero.png",
    "tagline": "Vaults for creator coins.",
    "ogTitle": "Creator Vaults",
    "ogDescription": "Deposit creator coins into vaults. Earn from trading fees. Everyone earns together.",
    "ogImageUrl": "https://4626.fun/miniapp-hero.png",
    "noindex": false
  }
}
